mcp_min/__init__.py
mcp_min/exceptions.py
mcp_min/types.py
mcp_min/server/__init__.py
mcp_min/server/exceptions.py
mcp_min/server/prompts/__init__.py
mcp_min/server/prompts/base.py
mcp_min/server/prompts/manager.py
mcp_min/server/resources/__init__.py
mcp_min/server/resources/base.py
mcp_min/server/resources/helpers.py
mcp_min/server/resources/manager.py
mcp_min/server/resources/templates.py
mcp_min/server/resources/types.py
mcp_min/server/tools/__init__.py
mcp_min/server/tools/base.py
mcp_min/server/tools/manager.py
mcp_min/server/utilities/content.py
mcp_min/server/utilities/func_metadata.py
mcp_min/server/utilities/types.py
mcp_min-20241105.160.0.dist-info/METADATA
mcp_min-20241105.160.0.dist-info/WHEEL
mcp_min-20241105.160.0.dist-info/licenses/LICENSE
mcp_min-20241105.160.0.dist-info/RECORD
