Metadata-Version: 2.4
Name: mcp-min
Version: 20241105.160.0
Summary: Model Context Protocol minimal SDK
Project-URL: Homepage, https://github.com/gi0baro/py-mcp-min
Project-URL: Source, https://github.com/gi0baro/py-mcp-min
Project-URL: Issues, https://github.com/gi0baro/py-mcp-min/issues
Author-email: Giovanni Barillari <g@baro.dev>
License-Expression: MIT
License-File: LICENSE
Keywords: automation,llm,mcp
Classifier: Development Status :: 4 - Beta
Classifier: Intended Audience :: Developers
Classifier: License :: OSI Approved :: MIT License
Classifier: Operating System :: OS Independent
Classifier: Programming Language :: Python :: 3
Classifier: Programming Language :: Python :: 3.9
Classifier: Programming Language :: Python :: 3.10
Classifier: Programming Language :: Python :: 3.11
Classifier: Programming Language :: Python :: 3.12
Classifier: Programming Language :: Python :: 3.13
Requires-Python: >=3.9
Requires-Dist: pydantic~=2.7
